README.rst
pyproject.toml
setup.py
libotp.egg-info/PKG-INFO
libotp.egg-info/SOURCES.txt
libotp.egg-info/dependency_links.txt
libotp.egg-info/top_level.txt
otp/__init__.py
otp/command.py
otp/object.py
otp/persist.py
otp/runtime.py