Metadata-Version: 2.1
Name: libotp
Version: 3
Summary: Office of the Prosecutor Communication 117 of the year 2019
Author-email: Bart Thate <record11719@gmail.com>
License: Public Domain
Project-URL: home, https://pypi.org/project/libotp
Project-URL: bugs, https://github.com/otpcr/libotp/issues
Project-URL: source, https://github.com/otpcr/libotp
Classifier: Development Status :: 4 - Beta
Classifier: License :: Public Domain
Classifier: Operating System :: Unix
Classifier: Programming Language :: Python :: 3
Classifier: Topic :: Utilities
